README.md
setup.cfg
setup.py
client/__init__.py
client/client.py
deploybot_client.egg-info/PKG-INFO
deploybot_client.egg-info/SOURCES.txt
deploybot_client.egg-info/dependency_links.txt
deploybot_client.egg-info/not-zip-safe
deploybot_client.egg-info/requires.txt
deploybot_client.egg-info/top_level.txt
test/__init__.py
test/client_test.py