Metadata-Version: 1.0
Name: deploybot-client
Version: 0.0.3
Summary: Deploybot API Client
Home-page: https://github.com/mrprompt/deploybot-client
Author: Thiago Paes
Author-email: mrprompt@gmail.com
License: GPL
Keywords: deploy,service,api,client,sdk,deploybot,continuous,delivery,cd
Platform: UNKNOWN
